MANIFEST.in
README
README.md
requirements.txt
setup.cfg
setup.py
tbone/__init__.py
tbone/utils.py
tbone.egg-info/PKG-INFO
tbone.egg-info/SOURCES.txt
tbone.egg-info/dependency_links.txt
tbone.egg-info/requires.txt
tbone.egg-info/top_level.txt
tbone/data/__init__.py
tbone/data/models.py
tbone/data/fields/__init__.py
tbone/data/fields/base.py
tbone/data/fields/composite.py
tbone/data/fields/mongo.py
tbone/data/fields/network.py
tbone/data/fields/phone_number.py
tbone/data/fields/simple.py
tbone/db/__init__.py
tbone/db/gis.py
tbone/db/models.py
tbone/dispatch/__init__.py
tbone/dispatch/signals.py
tbone/dispatch/carriers/__init__.py
tbone/dispatch/carriers/aiohttp_websocket.py
tbone/dispatch/carriers/sanic_websocket.py
tbone/dispatch/channels/__init__.py
tbone/dispatch/channels/mem.py
tbone/dispatch/channels/mongo.py
tbone/resources/__init__.py
tbone/resources/aiohttp.py
tbone/resources/authentication.py
tbone/resources/formatters.py
tbone/resources/http.py
tbone/resources/mongo.py
tbone/resources/resources.py
tbone/resources/routers.py
tbone/resources/sanic.py
tbone/resources/signals.py
tbone/testing/__init__.py
tbone/testing/clients.py
tbone/testing/fixtures.py
tbone/testing/resources.py
tests/__init__.py
tests/data/__init__.py
tests/data/test_composite_fields.py
tests/data/test_extra_fields.py
tests/data/test_fields.py
tests/data/test_models.py
tests/db/__init__.py
tests/db/models.py
tests/db/test_fields.py
tests/db/test_models.py
tests/dispatch/__init__.py
tests/dispatch/test_channels.py
tests/fixtures/__init__.py
tests/resources/__init__.py
tests/resources/resources.py
tests/resources/test_mongo_resources.py
tests/resources/test_resources.py