Metadata-Version: 1.2
Name: tbone
Version: 0.5.0.4
Summary: Full-duplex RESTful APIs for asyncio web applications
Home-page: https://github.com/475Cumulus/TBone
Author: 475 Cumulus Ltd.
Author-email: dev@475cumulus.com
License: MIT
Platform: UNKNOWN
Classifier: Environment :: Web Environment
Classifier: Framework :: AsyncIO
Classifier: License :: OSI Approved :: MIT License
Classifier: Intended Audience :: Developers
Classifier: Development Status :: 3 - Alpha
Classifier: Programming Language :: Python :: 3.5
Classifier: Programming Language :: Python :: 3.6
Classifier: Operating System :: POSIX
Classifier: Operating System :: MacOS :: MacOS X
Classifier: Operating System :: Microsoft :: Windows
Classifier: Topic :: Internet :: WWW/HTTP
Requires-Python: >=3.5.0
